Metadata-Version: 2.1
Name: odoo11-addon-queue-job
Version: 11.0.1.4.0
Summary: Job Queue
Home-page: https://github.com/OCA/queue/queue_job
Author: Camptocamp,ACSONE SA/NV,Odoo Community Association (OCA)
Author-email: support@odoo-community.org
License: LGPL-3
Platform: UNKNOWN
Classifier: Programming Language :: Python
Classifier: Framework :: Odoo
Classifier: Framework :: Odoo :: 11.0
Classifier: License :: OSI Approved :: GNU Lesser General Public License v3 (LGPLv3)
Classifier: Development Status :: 6 - Mature
Requires-Python: >=2.7, !=3.0.*, !=3.1.*, !=3.2.*, !=3.3.*, !=3.4.*
Requires-Dist: odoo (<11.1dev,>=11.0a)
Requires-Dist: requests
